Metadata-Version: 2.1
Name: kenu
Version: 1.3.4
Summary: Python kenu
Author: r4isy
Author-email: r4isy@kenucorp.com
